LICENSE.txt
MANIFEST.in
README.md
requirements.txt
setup.cfg
setup.py
siscad/Siscad.py
siscad/__init__.py
siscad/_version.py
siscad/utils.py
siscad.egg-info/PKG-INFO
siscad.egg-info/SOURCES.txt
siscad.egg-info/dependency_links.txt
siscad.egg-info/requires.txt
siscad.egg-info/top_level.txt
siscad/model/Disciplina.py
siscad/model/Frequencia.py
siscad/model/Nota.py
siscad/model/Semestre.py
siscad/model/__init__.py