Metadata-Version: 2.1
Name: siscad
Version: 0.0.5
Summary: Module for siscad.ufms.br
Home-page: https://github.com/llpinokio/siscad.py
Author: Giuliano Oliveira De Macedo
Author-email: giuliano.llpinokio@gmail.com
License: GPLv3
Download-URL: https://github.com/llpinokio/siscad.py/archive/v0.0.5.tar.gz
Keywords: web-scraping
Platform: UNKNOWN
Classifier: Development Status :: 4 - Beta
Classifier: Programming Language :: Python :: 3
Classifier: License :: OSI Approved :: GNU General Public License v3 (GPLv3)
Classifier: Operating System :: OS Independent
